mercapi_shops/__init__.py
mercapi_shops/mapping.py
mercapi_shops/mercapi_shops.py
mercapi_shops/models.py
mercapi_shops/py.typed
mercapi_shops/requests.py
mercapi_shops-0.0.5.dist-info/licenses/LICENSE
mercapi_shops-0.0.5.dist-info/METADATA
mercapi_shops-0.0.5.dist-info/WHEEL
mercapi_shops-0.0.5.dist-info/top_level.txt
mercapi_shops-0.0.5.dist-info/RECORD
