Metadata-Version: 2.4
Name: mercapi-shops
Version: 0.0.5
Summary: Unofficial Mercari Shops async client (jp.mercari.com / mercari-shops.com)
Author: EricMeteorite
License: MIT License
Project-URL: Homepage, https://github.com/EricMeteorite
Project-URL: Repository, https://github.com/EricMeteorite/mercapi_shops
Project-URL: Issues, https://github.com/EricMeteorite/mercapi_shops/issues
Keywords: mercari,mercari-shops,mercari-shops.com,jp.mercari.com,graphql,async,httpx,dpop
Classifier: Programming Language :: Python :: 3
Classifier: Programming Language :: Python :: 3 :: Only
Classifier: Programming Language :: Python :: 3.10
Classifier: Programming Language :: Python :: 3.11
Classifier: Programming Language :: Python :: 3.12
Classifier: Framework :: AsyncIO
Classifier: Typing :: Typed
Classifier: License :: OSI Approved :: MIT License
Classifier: Operating System :: OS Independent
Classifier: Intended Audience :: Developers
Classifier: Topic :: Internet :: WWW/HTTP
Requires-Python: >=3.10
License-File: LICENSE
Requires-Dist: httpx[http2]<0.28,>=0.24
Requires-Dist: cryptography<45,>=42
Provides-Extra: dev
Requires-Dist: pytest>=7; extra == "dev"
Requires-Dist: pytest-asyncio>=0.23; extra == "dev"
Requires-Dist: pytest-cov>=4; extra == "dev"
Requires-Dist: ruff>=0.5; extra == "dev"
Requires-Dist: mypy>=1.10; extra == "dev"
Requires-Dist: types-requests; extra == "dev"
Provides-Extra: speedups
Requires-Dist: uvloop>=0.17; sys_platform == "linux" and extra == "speedups"
Requires-Dist: brotlicffi>=1.1.0; platform_python_implementation != "PyPy" and extra == "speedups"
Dynamic: license-file
